context/__init__.py
context/context.py
ctxt-0.0.2.dist-info/LICENSE.txt
ctxt-0.0.2.dist-info/METADATA
ctxt-0.0.2.dist-info/WHEEL
ctxt-0.0.2.dist-info/top_level.txt
ctxt-0.0.2.dist-info/RECORD
