Metadata-Version: 2.1
Name: ctxt
Version: 0.0.2
Summary: Very simpler debugger providing context
Home-page: https://github.com/jeertmans/context
Author: Jérome Eertmans
Author-email: jeertmans@icloud.com
License: MIT
Keywords: debug,context,print
Platform: UNKNOWN
Classifier: Programming Language :: Python :: 3
Classifier: License :: OSI Approved :: MIT License
Classifier: Operating System :: OS Independent
Requires-Python: >=3.6
